unifi2mqtt/__init__.py
unifi2mqtt/__main__.py
unifi2mqtt/core.py
unifi2mqtt/setup.py
unifi2mqtt/lib/__init__.py
unifi2mqtt/lib/app_argparse.py
unifi2mqtt/lib/app_constants.py
unifi2mqtt/lib/app_settings.py
unifi2mqtt/lib/client.py
unifi2mqtt/lib/unifi.py
unifi2mqtt/lib/utils.py
unifi2mqtt-0.3.1.dist-info/licenses/LICENSE
unifi2mqtt-0.3.1.dist-info/METADATA
unifi2mqtt-0.3.1.dist-info/WHEEL
unifi2mqtt-0.3.1.dist-info/entry_points.txt
unifi2mqtt-0.3.1.dist-info/top_level.txt
unifi2mqtt-0.3.1.dist-info/RECORD
