Metadata-Version: 2.4
Name: unifi2mqtt
Version: 0.3.1
Summary: Monitor Unifi clients and publish status to MQTT
Author-email: "Dave (aka FreakErn)" <github@freakern.de>
Requires-Python: >=3.7
License-File: LICENSE
Requires-Dist: requests
Requires-Dist: paho-mqtt
Dynamic: license-file
